Lab10/E.v
//Ejerccicio 1
//couenter
module counter #(parameter N=12)
		(input logic clk, input logic reset, input logic load, input logic enabled, input [11:0] d, output logic [N-1:0]q);

always@(posedge clk, posedge reset)
	if(reset)
		q<=0;
	else if (load)
		q<=d;
	else if (enabled && !load)
		q<=q+1;

endmodule

//ROM
module memoria_ROM (input wire [11:0]addres, output wire [7:0]data);

	reg [7:0]mem[0:4095];

initial begin
	$readmemb("memoria.list",mem);
end

assign data = mem[addres];

endmodule


//f.f.D
module fetch(input clk, input reset, input ena, input [7:0]d, output reg [3:0]instruccion, output reg [3:0]operando);


	always @ (posedge clk, posedge reset)begin

		if (reset)
			begin
				operando <= 4'b0;
				instruccion <= 4'b0;
			end
		else if (ena)
			begin
				operando <= d[3:0];
				instruccion <= d[7:4];
			end
	end
endmodule



//preparacion de control

module preparacion(input clk, input reset,
		   input logic load_counter, input logic ena_load_counter,
		   input logic enabled_ct, input logic enabled_fetch,
		   input logic [11:0]in_dato,
		   output wire [7:0]program_byte, output wire [3:0]intsr, output wire [3:0]oprnd);


	output wire [11:0]out_counter;

	counter co1(.clk(clk), .reset(reset),
		    .load(ena_load_counter), .enabled(enabled_ct),
		    .d(in_dato),
		    .q(out_counter) );




	wire [7:0]out_ROM;

	memoria_ROM r1(.addres(out_counter), .data(out_ROM) );



	output wire [3:0]fetch_instruccions;
	output wire [3:0]fetch_operando;

	fetch ftc(.clk(clk), .reset(reset),
		  .ena(enabled_fetch),
		  .d(out_ROM),
		  .instruccion(fetch_instruccions), .operando(fetch_operando) );

assign program_byte = out_ROM;
assign intsr = fetch_instruccions;
assign oprnd = fetch_operando;

endmodule





//Ejerccicio 2
module buftri(input ena, input [3:0]d, output logic [3:0]q);

	always @ (*)
		if (ena == 0)
			q <= 1'bz;
		else
			q <= d;
endmodule


module accu(input clk, input reset, input ena, input [3:0]d, output logic [3:0]q);

	always @ (posedge clk, posedge reset)
		if (reset)
			q <= 4'b0;
		else if (ena)
			q <= d;
endmodule


module ALU (input wire [3:0] A,B,
	    input wire [2:0] funcion,
	    output logic[3:0] resul,
			output reg carry, zero);

reg[4:0] Alu_resultado;
parameter f1 = 3'b000;
parameter f2 = 3'b001;
parameter f3 = 3'b010;
parameter f4 = 3'b011;
parameter f5 = 3'b100;

always@(*) begin
	case(funcion)
		f1:
			Alu_resultado = A;
		f2:
			Alu_resultado = A - B;
		f3:
			Alu_resultado = B;
		f4:
			Alu_resultado = A + B;
		f5:
			Alu_resultado = ~(A & B);

		default: Alu_resultado = A + B;
	endcase

	assign resul = Alu_resultado;
	assign carry = Alu_resultado[4];
	assign zero = (Alu_resultado == 4'b0)? 4'd1:4'd0;

end
endmodule



module operacion(input clk, input reset, input [3:0]dato_in, input enabled_tri_1, input enabled_tri_2, input enabled_acu,  input [2:0] funcion, output [3:0]dato_out, output carry, zero);

	wire [3:0]salida_bufer_in;

	buftri datos_entrada(enabled_tri_1, dato_in, salida_bufer_in);


	wire [3:0]salida_alu;
	wire [3:0]salida_accu;

	accu acumulador(clk, reset, enabled_acu, salida_alu,	salida_accu);


	ALU	alu1(salida_accu, salida_bufer_in, funcion, salida_alu, carry, zero);


	buftri datos_salida(enabled_tri_2, salida_alu, dato_out);

endmodule

Lab10/Lab10/E1/E1_tb.v
// -----------------------------------
// José Alejandro Garía Aguirre
// Digital 
// lab10
// -----------------------------------
// Ejerccicio 1 TB

module testbench();

reg clk = 0;
reg reset = 0;
reg ena_load_counter = 0;
reg loadCounter = 0;
reg enabledCounter = 0;
reg enabled_fetch = 0;
reg [11:0]dato;

//ejercicio1
output wire[7:0]Program_byte;
output wire[3:0]instruccion;
output wire[3:0]operando;

preparacion part1(clk, reset, loadCounter, ena_load_counter, enabledCounter,  enabled_fetch, dato, Program_byte, instruccion, operando );

initial begin
	$display(" ");
	$display(" LOAD COUNTER    | Program byte  |   Instruccion   |  Operando  |");
	$display("----------------|---------------|-----------------|------------|");
	$monitor("%b               |  %b     |   %b          |    %b    |", loadCounter, Program_byte, instruccion, operando);

	reset = 1; #1 reset = 0; #1 dato = 12'b000011100000;
	#5 enabledCounter = 1;
	#5 ena_load_counter = 1; #2 ena_load_counter = 0;
	#5 enabled_fetch = 1;
	#5 reset = 1; #1 reset = 0;
	#5 dato = 12'b000000111000; #1 ena_load_counter = 1; #2 ena_load_counter = 0;
end

    initial
      #40 $finish;
    initial begin
        $dumpfile("E1_tb.vcd");
        $dumpvars(0, testbench);
      end
  endmodule

Lab10/E1.vcd
$date
	Fri Nov 06 12:41:44 2020
$end
$version
	Icarus Verilog
$end
$timescale
	1ps
$end
$scope module testbench $end
$var wire 4 ! operando [3:0] $end
$var wire 4 " instruccion [3:0] $end
$var wire 8 # Program_byte [7:0] $end
$var reg 1 $ clk $end
$var reg 12 % dato [11:0] $end
$var reg 1 & ena_load_counter $end
$var reg 1 ' enabledCounter $end
$var reg 1 ( enabled_fetch $end
$var reg 1 ) loadCounter $end
$var reg 1 * reset $end
$scope module part1 $end
$var wire 1 $ clk $end
$var wire 1 & ena_load_counter $end
$var wire 1 ' enabled_ct $end
$var wire 1 ( enabled_fetch $end
$var wire 12 + in_dato [11:0] $end
$var wire 4 , intsr [3:0] $end
$var wire 1 ) load_counter $end
$var wire 4 - oprnd [3:0] $end
$var wire 8 . program_byte [7:0] $end
$var wire 1 * reset $end
$var wire 12 / out_counter [11:0] $end
$var wire 8 0 out_ROM [7:0] $end
$var wire 4 1 fetch_operando [3:0] $end
$var wire 4 2 fetch_instruccions [3:0] $end
$scope module co1 $end
$var wire 1 $ clk $end
$var wire 12 3 d [11:0] $end
$var wire 1 ' enabled $end
$var wire 1 & load $end
$var wire 1 * reset $end
$var reg 12 4 q [11:0] $end
$upscope $end
$scope module ftc $end
$var wire 1 $ clk $end
$var wire 1 ( ena $end
$var wire 1 * reset $end
$var wire 8 5 d [7:0] $end
$var reg 4 6 instruccion [3:0] $end
$var reg 4 7 operando [3:0] $end
$upscope $end
$scope module r1 $end
$var wire 12 8 addres [11:0] $end
$var wire 8 9 data [7:0] $end
$upscope $end
$upscope $end
$upscope $end
$enddefinitions $end
#0
$dumpvars
bx 9
b0 8
b0 7
b0 6
bx 5
b0 4
bx 3
b0 2
b0 1
bx 0
b0 /
bx .
b0 -
b0 ,
bx +
1*
0)
0(
0'
0&
bx %
0$
bx #
b0 "
b0 !
$end
#1
0$
0*
#2
1$
b11100000 %
b11100000 +
b11100000 3
#3
0$
1'
#4
b11100000 /
b11100000 4
b11100000 8
1$
1&
#5
0$
#6
b11100001 /
b11100001 4
b11100001 8
1$
0&
#7
0$
1(
#8
bx "
bx ,
bx 2
bx 6
bx !
bx -
bx 1
bx 7
b11100010 /
b11100010 4
b11100010 8
1$
#9
0$
#10
b11100011 /
b11100011 4
b11100011 8
1$
#11
0$
#12
b0 "
b0 ,
b0 2
b0 6
b0 !
b0 -
b0 1
b0 7
b0 /
b0 4
b0 8
1$
1*
#13
0$
0*
#14
b1 /
b1 4
b1 8
bx "
bx ,
bx 2
bx 6
bx !
bx -
bx 1
bx 7
1$
b111000 %
b111000 +
b111000 3
#15
0$
1&
#16
b111000 /
b111000 4
b111000 8
1$
#17
0$
0&
#18
b111001 /
b111001 4
b111001 8
1$
#19
0$
#20
b111010 /
b111010 4
b111010 8
1$
