Lab8/Ejercicio 1/E1.v
//Alejandro García - 19163
//Lab 08 Ejercicio 1
//24-10-2020

//Modulo sumador
module contador #(parameter N=12)
		(input clk, reset, load, enabled, input [11:0] valor, output logic [N-1:0]resultado);

always@(posedge clk, posedge reset)
	if(reset)
		resultado<=0;
	else if (load)
		resultado<=valor;
	else if (enabled && !load)
		resultado<=resultado+1;

endmodule

Lab8/Ejercicio 1/E1_tb.v
//Alejandro García - 19163
//Lab 08 Ejercicio 1 TB
//24-10-2020

module testbench();
//Entradas
reg clk = 0;
reg reset = 1;
reg load = 0;
reg enabled = 0;
reg [11:0]valor;

//Salidas
output wire[11:0]resultado;

contador c1(clk, reset, load, enabled, valor, resultado);

//Datos iniciales
initial begin
	#1 reset = 0;
	#1 valor = 12'b110000001111;
	#3 enabled = 1;
	#2 load = 1; 
	#1 load = 0; 
	#6 enabled = 0; 
	#1 valor = 12'b101100011100;
	#5 enabled = 1;
	#4 load = 1;
	#2 load = 0;
end

always@(*)begin
	#1 clk = ~clk;
end

initial
	#50 $finish;		

//GTK WAVE
initial begin
	$dumpfile("E1_tb.vcd");
	$dumpvars(0, testbench);
	end
endmodule

Lab8/Ejercicio 1/E1_tb.vcd
$date
	Sat Oct 24 18:39:53 2020
$end
$version
	Icarus Verilog
$end
$timescale
	1ps
$end
$scope module testbench $end
$var wire 12 ! resultado [11:0] $end
$var reg 1 " clk $end
$var reg 1 # enabled $end
$var reg 1 $ load $end
$var reg 1 % reset $end
$var reg 12 & valor [11:0] $end
$scope module c1 $end
$var wire 1 " clk $end
$var wire 1 # enabled $end
$var wire 1 $ load $end
$var wire 1 % reset $end
$var wire 12 ' valor [11:0] $end
$var reg 12 ( resultado [11:0] $end
$upscope $end
$upscope $end
$enddefinitions $end
#0
$dumpvars
b0 (
bx '
bx &
1%
0$
0#
0"
b0 !
$end
#1
1"
0%
#2
b110000001111 &
b110000001111 '
#5
1#
#7
1$
#8
0$
#14
0#
#15
b101100011100 &
b101100011100 '
#20
1#
#24
1$
#26
0$
