Lab3/Tabla_4_SOP/Tabla_4_SOP.v
// -----------------------------------
// José Alejandro Garía Aguirre
// Digital 
// Tabla_4_SOP
// -----------------------------------
module Tabla_4_SOP();	// nombre módulo
  
//   Elementos
 reg A, B, C, D;
 wire w1,w2,w3,w4,w5,w6,w7,w8,w9,w10,w11, Y;
// compuertas    
not U1 (w1, A);					//A'
not U2 (w2, B);					//B'
not U3 (w3, C);					//C'
not U4 (w4, D);					//D'
and A1 (w5, w1, w2, w3, w4);	//a'b'c'd'
and A2 (w6, w1, w2, C, w4);		//a'b'cd'
and A3 (w7, w1, w2, C, D);		//a'b'cd
and A4 (w8, w1, B, C, w4);		//a'bcd'
and A5 (w9, w1, B, C, D);		//a'bcd
and A6 (w10, A, w2, w3, w4);	//ab'c'd'
and A7 (w11, A, w2, C, w4);		//ab'cd'
or  O1 (Y, w5,w6,w7,w8,w9,w10,w11); 	//Salida

// Simulacion
initial begin	// inicio simulacion
  $monitor(
  "Time%d: A=%b B=%b C=%b D=%b Y=%b", 
    $time, A,B,C,D,Y); 
  // Valores iniciales
  A = 0; B = 0; C = 0; D = 0;
  // Cambios en otros tiempo
  #1 A = 0; B = 0; C = 0; D = 1;
  #1 A = 0; B = 0; C = 1; D = 0;
  #1 A = 0; B = 0; C = 1; D = 1;
  #1 A = 0; B = 1; C = 0; D = 0;
  #1 A = 0; B = 1; C = 0; D = 1;
  #1 A = 0; B = 1; C = 1; D = 0;
  #1 A = 0; B = 1; C = 1; D = 1;
  #1 A = 1; B = 0; C = 0; D = 0;
  #1 A = 1; B = 0; C = 0; D = 1;
  #1 A = 1; B = 0; C = 1; D = 0;
  #1 A = 1; B = 0; C = 1; D = 1;
  #1 A = 1; B = 1; C = 0; D = 0;
  #1 A = 1; B = 1; C = 0; D = 1;
  #1 A = 1; B = 1; C = 1; D = 0;
  #1 A = 1; B = 1; C = 1; D = 1;
  #1 $finish;   // termina la simulación
  end	

 
  initial 
    begin
      $dumpfile("Tabla_4_SOP_tb.vcd");
      $dumpvars(0,Tabla_4_SOP);
    end 
endmodule

Lab3/Tabla_4_SOP/Tabla_4_SOP_tb.vcd
$date
	Sat Aug 01 22:27:17 2020
$end
$version
	Icarus Verilog
$end
$timescale
	1ps
$end
$scope module Tabla_4_SOP $end
$var wire 1 ! Y $end
$var wire 1 " w1 $end
$var wire 1 # w10 $end
$var wire 1 $ w11 $end
$var wire 1 % w2 $end
$var wire 1 & w3 $end
$var wire 1 ' w4 $end
$var wire 1 ( w5 $end
$var wire 1 ) w6 $end
$var wire 1 * w7 $end
$var wire 1 + w8 $end
$var wire 1 , w9 $end
$var reg 1 - A $end
$var reg 1 . B $end
$var reg 1 / C $end
$var reg 1 0 D $end
$upscope $end
$enddefinitions $end
#0
$dumpvars
00
0/
0.
0-
0,
0+
0*
0)
1(
1'
1&
1%
0$
0#
1"
1!
$end
#1
0!
0(
0'
10
#2
1!
1)
1'
0&
00
1/
#3
0)
1*
0'
10
#4
0!
1'
0*
1&
0%
00
0/
1.
#5
0'
10
#6
1!
1+
1'
0&
00
1/
#7
0+
1,
0'
10
#8
1#
1'
1&
0,
1%
0"
00
0/
0.
1-
#9
0!
0#
0'
10
#10
1!
1$
1'
0&
00
1/
#11
0!
0$
0'
10
#12
1'
1&
0%
00
0/
1.
#13
0'
10
#14
1'
0&
00
1/
#15
0'
10
