Lab3/Tabla_2_POS/Tabla_2_POS.v
// -----------------------------------
// José Alejandro Garía Aguirre
// Digital 
// Tabla_2_POS
// -----------------------------------
module Tabla_2_POS();	// nombre módulo
  
//Elementos   
 reg A, B, C;
 wire w1,w2,w3,w4,w5,w6,w7,w8,Y;
// compuertas    
not U1 (w1, A);					//A'
not U2 (w2, B);					//B'
not U3 (w3, C);					//C'
or  o1 (w4, A, B, C);				//A+B+C
or  o2 (w5, A, W2, C);				//A+B'+C
or  o3 (w6, A, w2, w3);				//A'+B+C
or  o4 (w7, w1, B, C);				//A'+B+C	
or  o5 (w8, w1, B, w3);				//A'+B+C'
and a1 (Y, w4, w5, w6, w7, w8);	//Respuesta	

// Simulacion
initial begin	// inicio simulacion
  $monitor(
  "Time%d: A=%b B=%b C=%b Y=%b", 
    $time, A,B,C,Y); 
  // Valores iniciales
  A = 0; B = 0; C = 0;
  // Cambios en otros tiempo
  #1 A = 0; B = 0; C = 1;
  #1 A = 0; B = 1; C = 0;
  #1 A = 0; B = 1; C = 1;
  #1 A = 1; B = 0; C = 0;
  #1 A = 1; B = 0; C = 1;
  #1 A = 1; B = 1; C = 0;
  #1 A = 1; B = 1; C = 1;
  #1 $finish;   // termina la simulación
end	

 
  initial 
    begin
      $dumpfile("Tabla_2_POS_tb.vcd");
      $dumpvars(0,Tabla_2_POS);
    end 
endmodule

Lab3/Tabla_2_POS/Tabla_2_POS_tb.vcd
$date
	Sat Aug 01 22:32:28 2020
$end
$version
	Icarus Verilog
$end
$timescale
	1ps
$end
$scope module Tabla_2_POS $end
$var wire 1 ! W2 $end
$var wire 1 " Y $end
$var wire 1 # w1 $end
$var wire 1 $ w2 $end
$var wire 1 % w3 $end
$var wire 1 & w4 $end
$var wire 1 ' w5 $end
$var wire 1 ( w6 $end
$var wire 1 ) w7 $end
$var wire 1 * w8 $end
$var reg 1 + A $end
$var reg 1 , B $end
$var reg 1 - C $end
$upscope $end
$enddefinitions $end
#0
$dumpvars
0-
0,
0+
1*
1)
1(
x'
0&
1%
1$
1#
0"
z!
$end
#1
1"
1'
1&
0%
1-
#2
x"
x'
1%
0$
0-
1,
#3
0"
0(
1'
0%
1-
#4
1%
1*
0)
1$
1(
0#
0-
0,
1+
#5
0*
1)
0%
1-
#6
1"
1%
1*
0$
0-
1,
#7
0%
1-
