Lab3/Tabla_1_POS/Tabla_1_POS.v
// -----------------------------------
// José Alejandro Garía Aguirre
// Digital 
// Tabla_1_POS
// -----------------------------------
module Tabla_1_POS();	// nombre módulo
  
//   Elementos
 reg A, B, C;
 wire w1,w2,w3,w4,w5,w6, Y;
// compuertas    
not U1 (w1, A);					//A'
not U2 (w2, B);					//B'
not U3 (w3, C);					//C'
or o1 (w4, A, B, w3);				//a+b+c'
or o2 (w5, A, w2, w3);				//a+b'+c'
or o3 (w6, w1, w2, C);				//a'+b'+c
and a1 (Y, w4, w5, w6);			//respuesta

// Simulacion
initial begin	// inicio simulacion
  //monitor nos permite rastrear cambios en las entradas y salidas
  // %b = binario %d = decimal %h = hex  \t = tabulación
  $monitor(
  "Time%d: A=%b B=%b C=%b Y=%b", 
    $time, A,B,C,Y); 
  // Valores iniciales
  A = 0; B = 0; C = 0; 
  // Cambios en otros tiempo
  #1 A = 0; B = 0; C = 1;
  #1 A = 0; B = 1; C = 0;
  #1 A = 0; B = 1; C = 1;
  #1 A = 1; B = 0; C = 0;
  #1 A = 1; B = 0; C = 1;
  #1 A = 1; B = 1; C = 0;
  #1 A = 1; B = 1; C = 1;
  #1 $finish;   
end		// termina la simulación

 
  initial 
    begin
      $dumpfile("Tabla_1_POS_tb.vcd");
      $dumpvars(0,Tabla_1_POS);
    end 
endmodule

Lab3/Tabla_1_POS/Tabla_1_POS.vcd
$date
	Sat Aug 01 22:21:40 2020
$end
$version
	Icarus Verilog
$end
$timescale
	1ps
$end
$scope module Tabla_1_POS $end
$var wire 1 ! Y $end
$var wire 1 " w1 $end
$var wire 1 # w2 $end
$var wire 1 $ w3 $end
$var wire 1 % w4 $end
$var wire 1 & w5 $end
$var wire 1 ' w6 $end
$var reg 1 ( A $end
$var reg 1 ) B $end
$var reg 1 * C $end
$upscope $end
$enddefinitions $end
#0
$dumpvars
0*
0)
0(
1'
1&
1%
1$
1#
1"
1!
$end
#1
0!
0%
0$
1*
#2
1!
1$
1%
0#
0*
1)
#3
0!
0&
0$
1*
#4
1!
1$
1#
1&
0"
0*
0)
1(
#5
0$
1*
#6
0!
0'
1$
0#
0*
1)
#7
1!
1'
0$
1*
