Lab3/Tabla_4_POS/Tabla_4_POS.v
// -----------------------------------
// José Alejandro Garía Aguirre
// Digital 
// Tabla_4_POS
// -----------------------------------
module Tabla_4_POS();	// nombre módulo
  
//   Elementos
 reg A, B, C, D;
 wire w1,w2,w3,w4,w5,w6,w7,w8, Y;
// compuertas    
not U1 (w1, A);					//A'
not U2 (w2, B);					//B'
not U3 (w3, C);					//C'
not U4 (w3, D);					//D'
or  o1 (w5, A, B, C, w4);		//a+b+c+d'
or  o2 (w6, A, w2, C, D);		//a+b'+c+d
or  o3 (w7, A, w2, C, w4);		//a+b'+c+d'
or  o4 (w8, w1, B, C, w4);		//a'+b+c+d'
or  o5 (w9, w1, B, w3, w4);		//a'+b+c'+d'
or  o6 (w10, w1, w2, C, D);		//a'+b'+c+d
or  o7 (w11, w1, w2, C, w4);	//a'+b'+c+d'
or  o8 (w12, w1, w2, w3, D);	//a'+b'+c'+d
or  o9 (w13, w1, w2, w3, w4);	//a'+b'+c'+d'
and a1 (Y, w5,w6,w7,w8,w9,w10,w11,w12,w13); 	//Salida

// Simulacion
initial begin	// inicio simulacion
  $monitor(
  "Time%d: A=%b B=%b C=%b D=%b Y=%b", 
    $time, A,B,C,D,Y);
  // Valores iniciales
  A = 0; B = 0; C = 0; D = 0;
  // Cambios en otros tiempo
  #1 A = 0; B = 0; C = 0; D = 1;
  #1 A = 0; B = 0; C = 1; D = 0;
  #1 A = 0; B = 0; C = 1; D = 1;
  #1 A = 0; B = 1; C = 0; D = 0;
  #1 A = 0; B = 1; C = 0; D = 1;
  #1 A = 0; B = 1; C = 1; D = 0;
  #1 A = 0; B = 1; C = 1; D = 1;
  #1 A = 1; B = 0; C = 0; D = 0;
  #1 A = 1; B = 0; C = 0; D = 1;
  #1 A = 1; B = 0; C = 1; D = 0;
  #1 A = 1; B = 0; C = 1; D = 1;
  #1 A = 1; B = 1; C = 0; D = 0;
  #1 A = 1; B = 1; C = 0; D = 1;
  #1 A = 1; B = 1; C = 1; D = 0;
  #1 A = 1; B = 1; C = 1; D = 1;
  #1 $finish;   // termina la simulación
  end	

 
  initial 
    begin
      $dumpfile("Tabla_4_POS_tb.vcd");
      $dumpvars(0,Tabla_4_POS);
    end 
endmodule

Lab3/Tabla_4_POS/Tabla_4_POS.vcd
$date
	Sat Aug 01 14:37:31 2020
$end
$version
	Icarus Verilog
$end
$timescale
	1ps
$end
$scope module Tabla_4_POS $end
$var wire 1 ! Y $end
$var wire 1 " w1 $end
$var wire 1 # w10 $end
$var wire 1 $ w11 $end
$var wire 1 % w12 $end
$var wire 1 & w13 $end
$var wire 1 ' w2 $end
$var wire 1 ( w3 $end
$var wire 1 ) w4 $end
$var wire 1 * w5 $end
$var wire 1 + w6 $end
$var wire 1 , w7 $end
$var wire 1 - w8 $end
$var wire 1 . w9 $end
$var reg 1 / A $end
$var reg 1 0 B $end
$var reg 1 1 C $end
$var reg 1 2 D $end
$upscope $end
$enddefinitions $end
#0
$dumpvars
02
01
00
0/
1.
1-
1,
1+
x*
z)
1(
1'
1&
1%
1$
1#
1"
x!
$end
#1
x(
12
#2
1!
1*
x(
02
11
#3
0(
12
#4
0!
x,
0+
1(
0'
02
01
10
#5
x!
1+
x(
12
#6
1!
1,
x(
02
11
#7
0(
12
#8
x!
1(
1.
x-
1'
0"
02
01
00
1/
#9
x.
x(
12
#10
1-
x(
02
11
#11
0(
12
#12
0!
x$
0#
1(
1.
0'
02
01
10
#13
x!
x&
1#
x(
12
#14
x%
1$
x(
02
11
#15
1%
0(
12
