Lab9/Ejercicio 5/E5.v
//José Alejandro García Aguirre
//Lab9
//Ejecicio 5


module ROM(input wire [6:0]inp, output logic [12:0]outp);

reg[12:0] dato;

	always @(*) begin
		casez (inp)
			7'b??????0:
		 		dato = 13'b1000000001000;
			7'b00001?1: dato = 13'b0100000001000;
			7'b00000?1: dato = 13'b1000000001000;
			7'b00011?1: dato = 13'b1000000001000;
			7'b00010?1: dato = 13'b0100000001000;
			7'b0010??1: dato = 13'b0001001000010;
			7'b0011??1: dato = 13'b1001001100000;
			7'b0100??1: dato = 13'b0011010000010;
			7'b0101??1: dato = 13'b0011010000100;
			7'b0110??1: dato = 13'b1011010100000;
			7'b0111??1: dato = 13'b1000000111000;
			7'b1000?11: dato = 13'b0100000001000;
			7'b1000?01: dato = 13'b1000000001000;
			7'b1001?11: dato = 13'b1000000001000;
			7'b1001?01: dato = 13'b0100000001000;
			7'b1010??1: dato = 13'b0011011000010;
			7'b1011??1: dato = 13'b1011011100000;
			7'b1100??1: dato = 13'b0100000001000;
			7'b1101??1: dato = 13'b0000000001001;
			7'b1110??1: dato = 13'b0011100000010;
			7'b1111??1: dato = 13'b1011100100000;
			default: dato = 13'bxxxxxxxxxxxxx;			
		endcase
		assign outp = dato;
end
endmodule

Lab9/Ejercicio 5/E5_tb.v
//José Alejandro García Aguirre
//Lab9
//Ejecicio 5 tb

module testbench();

reg [6:0]inp;
output wire [12:0]outp;

ROM zucker(inp, outp);

initial begin
	#1 $display("-----------------------");
	#1 $display("---------Lab 9---------");
	#1 $display(" Input  | Output");
	#1 inp = 7'b0000000;
	#3 $display("%b | %b", inp, outp);
	
	#1 inp = 7'b00001;
	#3 $display("%b | %b", inp, outp);
	
	#1 inp = 7'b0000001;
	#3 $display("%b | %b", inp, outp);

	#1 inp = 7'b0001101;
	#3 $display("%b | %b", inp, outp);

	#1 inp = 7'b0001001;
	#3 $display("%b | %b", inp, outp);

	#1 inp = 7'b0010001;
	#3 $display("%b | %b", inp, outp);

	#1 inp = 7'b0011001;
	#3 $display("%b | %b", inp, outp);

	#1 inp = 7'b0100001;
	#3 $display("%b | %b", inp, outp);

	#1 inp = 7'b0101001;
	#3 $display("%b | %b", inp, outp);

	#1 inp = 7'b0110001;
	#3 $display("%b | %b", inp, outp);

	#1 inp = 7'b0111001;
	#3 $display("%b | %b", inp, outp);

	#1 inp = 7'b1000011;
	#3 $display("%b | %b", inp, outp);

	#1 inp = 7'b1000001;
	#3 $display("%b | %b", inp, outp);

	#1 inp = 7'b1001011;
	#3 $display("%b | %b", inp, outp);

	#1 inp = 7'b1001001;
	#3 $display("%b | %b", inp, outp);

	#1 inp = 7'b1010001;
	#3 $display("%b | %b", inp, outp);

	#1 inp = 7'b1011001;
	#3 $display("%b | %b", inp, outp);

	#1 inp = 7'b1100001;
	#3 $display("%b | %b", inp, outp);

	#1 inp = 7'b1101001;
	#3 $display("%b | %b", inp, outp);

	#1 inp = 7'b1110001;
	#3 $display("%b | %b", inp, outp);

	#1 inp = 7'b1111001;
	#3 $display("%b | %b", inp, outp);

	#1 inp = 7'b1010101;
	#3 $display("%b | %b", inp, outp);

	#1 inp = 7'b0101010;
	#3 $display("%b | %b", inp, outp);

	#1 inp = 7'b1001101;
	#3 $display("%b | %b", inp, outp);

	#1 inp = 7'b1000111;
	#3 $display("%b | %b", inp, outp);

	#1 inp = 7'b0111011;
	#3 $display("%b | %b", inp, outp);

	#1 inp = 7'b1111111;
	#3 $display("%b | %b", inp, outp);

	#1 inp = 7'b1111110;
	#3 $display("%b | %b", inp, outp);
end



initial
	#120 $finish;		
initial begin
	$dumpfile("E5_tb.vcd");
	$dumpvars(0, testbench);
	end
endmodule

Lab9/Ejercicio 5/E5_tb.vcd
$date
	Sat Oct 31 02:04:04 2020
$end
$version
	Icarus Verilog
$end
$timescale
	1ps
$end
$scope module testbench $end
$var wire 13 ! outp [12:0] $end
$var reg 7 " inp [6:0] $end
$scope module zucker $end
$var wire 7 # inp [6:0] $end
$var reg 13 $ dato [12:0] $end
$var reg 13 % outp [12:0] $end
$upscope $end
$upscope $end
$enddefinitions $end
#0
$dumpvars
bx %
bx $
bx #
bx "
bx !
$end
#4
b1000000001000 !
b1000000001000 %
b1000000001000 $
b0 "
b0 #
#8
b1 "
b1 #
#16
b1101 "
b1101 #
#20
b100000001000 !
b100000001000 %
b100000001000 $
b1001 "
b1001 #
#24
b1001000010 !
b1001000010 %
b1001000010 $
b10001 "
b10001 #
#28
b1001001100000 !
b1001001100000 %
b1001001100000 $
b11001 "
b11001 #
#32
b11010000010 !
b11010000010 %
b11010000010 $
b100001 "
b100001 #
#36
b11010000100 !
b11010000100 %
b11010000100 $
b101001 "
b101001 #
#40
b1011010100000 !
b1011010100000 %
b1011010100000 $
b110001 "
b110001 #
#44
b1000000111000 !
b1000000111000 %
b1000000111000 $
b111001 "
b111001 #
#48
b100000001000 !
b100000001000 %
b100000001000 $
b1000011 "
b1000011 #
#52
b1000000001000 !
b1000000001000 %
b1000000001000 $
b1000001 "
b1000001 #
#56
b1001011 "
b1001011 #
#60
b100000001000 !
b100000001000 %
b100000001000 $
b1001001 "
b1001001 #
#64
b11011000010 !
b11011000010 %
b11011000010 $
b1010001 "
b1010001 #
#68
b1011011100000 !
b1011011100000 %
b1011011100000 $
b1011001 "
b1011001 #
#72
b100000001000 !
b100000001000 %
b100000001000 $
b1100001 "
b1100001 #
#76
b1001 !
b1001 %
b1001 $
b1101001 "
b1101001 #
#80
b11100000010 !
b11100000010 %
b11100000010 $
b1110001 "
b1110001 #
#84
b1011100100000 !
b1011100100000 %
b1011100100000 $
b1111001 "
b1111001 #
#88
b11011000010 !
b11011000010 %
b11011000010 $
b1010101 "
b1010101 #
#92
b1000000001000 !
b1000000001000 %
b1000000001000 $
b101010 "
b101010 #
#96
b100000001000 !
b100000001000 %
b100000001000 $
b1001101 "
b1001101 #
#100
b1000111 "
b1000111 #
#104
b1000000111000 !
b1000000111000 %
b1000000111000 $
b111011 "
b111011 #
#108
b1011100100000 !
b1011100100000 %
b1011100100000 $
b1111111 "
b1111111 #
#112
b1000000001000 !
b1000000001000 %
b1000000001000 $
b1111110 "
b1111110 #
